cassandra/__init__.py
cassandra/auth.py
cassandra/buffer.pxd
cassandra/bytesio.cpython-310-x86_64-linux-gnu.so
cassandra/bytesio.pxd
cassandra/bytesio.pyx
cassandra/cluster.cpython-310-x86_64-linux-gnu.so
cassandra/cluster.py
cassandra/cmurmur3.c
cassandra/cmurmur3.cpython-310-x86_64-linux-gnu.so
cassandra/concurrent.cpython-310-x86_64-linux-gnu.so
cassandra/concurrent.py
cassandra/connection.cpython-310-x86_64-linux-gnu.so
cassandra/connection.py
cassandra/cqltypes.cpython-310-x86_64-linux-gnu.so
cassandra/cqltypes.py
cassandra/cython_deps.py
cassandra/cython_marshal.cpython-310-x86_64-linux-gnu.so
cassandra/cython_marshal.pyx
cassandra/cython_utils.cpython-310-x86_64-linux-gnu.so
cassandra/cython_utils.pxd
cassandra/cython_utils.pyx
cassandra/deserializers.cpython-310-x86_64-linux-gnu.so
cassandra/deserializers.pxd
cassandra/deserializers.pyx
cassandra/encoder.py
cassandra/ioutils.cpython-310-x86_64-linux-gnu.so
cassandra/ioutils.pyx
cassandra/marshal.py
cassandra/metadata.cpython-310-x86_64-linux-gnu.so
cassandra/metadata.py
cassandra/metrics.py
cassandra/murmur3.py
cassandra/numpyFlags.h
cassandra/numpy_parser.cpython-310-x86_64-linux-gnu.so
cassandra/numpy_parser.pyx
cassandra/obj_parser.cpython-310-x86_64-linux-gnu.so
cassandra/obj_parser.pyx
cassandra/parsing.cpython-310-x86_64-linux-gnu.so
cassandra/parsing.pxd
cassandra/parsing.pyx
cassandra/policies.py
cassandra/pool.cpython-310-x86_64-linux-gnu.so
cassandra/pool.py
cassandra/protocol.cpython-310-x86_64-linux-gnu.so
cassandra/protocol.py
cassandra/query.cpython-310-x86_64-linux-gnu.so
cassandra/query.py
cassandra/row_parser.cpython-310-x86_64-linux-gnu.so
cassandra/row_parser.pyx
cassandra/segment.py
cassandra/timestamps.py
cassandra/tuple.pxd
cassandra/type_codes.pxd
cassandra/type_codes.py
cassandra/util.cpython-310-x86_64-linux-gnu.so
cassandra/util.py
cassandra/column_encryption/_policies.py
cassandra/column_encryption/policies.py
yb_cassandra_driver-3.29.1.1.dist-info/LICENSE
yb_cassandra_driver-3.29.1.1.dist-info/METADATA
yb_cassandra_driver-3.29.1.1.dist-info/NOTICE
yb_cassandra_driver-3.29.1.1.dist-info/WHEEL
yb_cassandra_driver-3.29.1.1.dist-info/top_level.txt
yb_cassandra_driver-3.29.1.1.dist-info/RECORD
