Metadata-Version: 2.1
Name: yb-cassandra-driver
Version: 3.29.1.1
Summary: DataStax Driver for YCQL YugabyteDB
Home-page: http://github.com/yugaByte/cassandra-python-driver
Author: yugabyte
Author-email: pypi@yugabyte.com
Project-URL: Documentation, https://docs.yugabyte.com/stable/drivers-orms/python/ycql/
Project-URL: Source, https://github.com/yugabyte/cassandra-python-driver/
Keywords: cassandra,cql,orm
Classifier: Development Status :: 5 - Production/Stable
Classifier: Intended Audience :: Developers
Classifier: License :: OSI Approved :: Apache Software License
Classifier: Natural Language :: English
Classifier: Operating System :: OS Independent
Classifier: Programming Language :: Python
Classifier: Programming Language :: Python :: 3.8
Classifier: Programming Language :: Python :: 3.9
Classifier: Programming Language :: Python :: 3.10
Classifier: Programming Language :: Python :: 3.11
Classifier: Programming Language :: Python :: 3.12
Classifier: Programming Language :: Python :: Implementation :: CPython
Classifier: Programming Language :: Python :: Implementation :: PyPy
Classifier: Topic :: Software Development :: Libraries :: Python Modules
License-File: LICENSE
License-File: NOTICE
Requires-Dist: geomet <0.3,>=0.1
Requires-Dist: wheel >=0.34.2
Provides-Extra: cle
Requires-Dist: cryptography >=35.0 ; extra == 'cle'
Provides-Extra: graph
Requires-Dist: gremlinpython ==3.4.6 ; extra == 'graph'
